README.rst
setup.py
django_gravatar/__init__.py
django_gravatar/settings.py
django_gravatar/templatetags/__init__.py
django_gravatar/templatetags/gravatar.py
django_simple_gravatar.egg-info/PKG-INFO
django_simple_gravatar.egg-info/SOURCES.txt
django_simple_gravatar.egg-info/dependency_links.txt
django_simple_gravatar.egg-info/top_level.txt