Metadata-Version: 1.1
Name: django-simple-gravatar
Version: 1.0.1
Summary: Django Gravatar is a lightweight Django application that allows you to insert a Gravatar image in your templates.
Home-page: https://github.com/skitoo/django-gravatar
Author: Alexis Couronne
Author-email: alexis.couronne@scopart.fr
License: New BSD License
Keywords: django gravatar avatar
Platform: OS Independent
Classifier: Development Status :: 5 - Production/Stable
Classifier: Environment :: Web Environment
Classifier: Framework :: Django
Classifier: Intended Audience :: Developers
Classifier: License :: OSI Approved :: BSD License
Classifier: Operating System :: OS Independent
Classifier: Programming Language :: Python
Classifier: Topic :: Internet :: WWW/HTTP :: Dynamic Content
Classifier: Topic :: Software Development
Classifier: Topic :: Software Development :: Libraries :: Application Frameworks
